cpenormalize/__init__.py
cpenormalize-0.0.1.dist-info/METADATA
cpenormalize-0.0.1.dist-info/WHEEL
cpenormalize-0.0.1.dist-info/top_level.txt
cpenormalize-0.0.1.dist-info/RECORD
