Metadata-Version: 2.1
Name: cpenormalize
Version: 0.0.1
Summary: Built-in functions, exceptions, and other objects.
Home-page: http://github.com/d33tah/cpenormalize
Author: Jacek "d33tah" Wielemborek
Author-email: d33tah@gmail.com
License: WTFPL
Requires-Dist: cpe
